Oggyz/__init__.py
Oggyz/colors.py
Oggyz/write.py
Oggyz-0.1.dist-info/METADATA
Oggyz-0.1.dist-info/WHEEL
Oggyz-0.1.dist-info/top_level.txt
Oggyz-0.1.dist-info/RECORD
