Metadata-Version: 2.1
Name: Oggyz
Version: 0.1
Summary: A custom text printing package with colors
Home-page: https://github.com/yourusername/Oggyz
Author: oggy
Author-email: tranthang20111@gmail.com
License: MIT
Classifier: Development Status :: 3 - Alpha
Classifier: Programming Language :: Python :: 3
Classifier: License :: OSI Approved :: MIT License
Classifier: Operating System :: OS Independent
Requires-Python: >=3.6
